README.md
setup.py
mcsample/__init__.py
mcsample/base.py
mcsample/prior.py
mcsample.egg-info/PKG-INFO
mcsample.egg-info/SOURCES.txt
mcsample.egg-info/dependency_links.txt
mcsample.egg-info/top_level.txt