Metadata-Version: 1.1
Name: mcsample
Version: 0.1.0
Summary: mcsample: MCMC Sample low level python tools 
Home-page: https://github.com/MickaelRigault/mcsample
Author: Mickael Rigault
Author-email: m.rigault@ipnl.in2p3.fr
License: Apache 2.0
Download-URL: https://github.com/MickaelRigault/mcsample/0.1
Platform: UNKNOWN
Classifier: Intended Audience :: Science/Research
Classifier: Programming Language :: Python :: 2.7
Classifier: Programming Language :: Python :: 3.5
Classifier: License :: OSI Approved :: BSD License
Classifier: Topic :: Scientific/Engineering :: Astronomy
Classifier: Operating System :: POSIX
Classifier: Operating System :: Unix
Classifier: Operating System :: MacOS
